pcp_serversdk_python/CommunicatorConfiguration.py
pcp_serversdk_python/RequestHeaderGenerator.py
pcp_serversdk_python/__init__.py
pcp_serversdk_python/endpoints/AuthenticationApiClient.py
pcp_serversdk_python/endpoints/BaseApiClient.py
pcp_serversdk_python/endpoints/CheckoutApiClient.py
pcp_serversdk_python/endpoints/CommerceCaseApiClient.py
pcp_serversdk_python/endpoints/OrderManagementCheckoutActionsApiClient.py
pcp_serversdk_python/endpoints/PaymentExecutionApiClient.py
pcp_serversdk_python/endpoints/PaymentInformationApiClient.py
pcp_serversdk_python/endpoints/__init__.py
pcp_serversdk_python/errors/ApiErrorResponseException.py
pcp_serversdk_python/errors/ApiException.py
pcp_serversdk_python/errors/ApiResponseRetrievalException.py
pcp_serversdk_python/errors/__init__.py
pcp_serversdk_python/models/APIError.py
pcp_serversdk_python/models/ActionType.py
pcp_serversdk_python/models/Address.py
pcp_serversdk_python/models/AddressPersonal.py
pcp_serversdk_python/models/AllowedPaymentActions.py
pcp_serversdk_python/models/AmountOfMoney.py
pcp_serversdk_python/models/ApplePaymentDataTokenHeaderInformation.py
pcp_serversdk_python/models/ApplePaymentDataTokenInformation.py
pcp_serversdk_python/models/ApplePaymentTokenVersion.py
pcp_serversdk_python/models/AppliedExemption.py
pcp_serversdk_python/models/AuthenticationToken.py
pcp_serversdk_python/models/AuthorizationMode.py
pcp_serversdk_python/models/AvsResult.py
pcp_serversdk_python/models/BankAccountInformation.py
pcp_serversdk_python/models/BankPayoutMethodSpecificInput.py
pcp_serversdk_python/models/BusinessRelation.py
pcp_serversdk_python/models/CancelItem.py
pcp_serversdk_python/models/CancelPaymentRequest.py
pcp_serversdk_python/models/CancelPaymentResponse.py
pcp_serversdk_python/models/CancelRequest.py
pcp_serversdk_python/models/CancelResponse.py
pcp_serversdk_python/models/CancelType.py
pcp_serversdk_python/models/CancellationReason.py
pcp_serversdk_python/models/CaptureOutput.py
pcp_serversdk_python-1.5.0.dist-info/licenses/LICENSE
pcp_serversdk_python-1.5.0.dist-info/METADATA
pcp_serversdk_python-1.5.0.dist-info/WHEEL
pcp_serversdk_python-1.5.0.dist-info/top_level.txt
pcp_serversdk_python-1.5.0.dist-info/RECORD
