Metadata-Version: 2.4
Name: pcp_serversdk_python
Version: 1.5.0
Home-page: https://github.com/PAYONE-GmbH/PCP-ServerSDK-python
Author: PAYONE-GmbH
Author-email: 
Keywords: payone,pcp,server,python,sdk
Classifier: Programming Language :: Python :: 3
Classifier: License :: OSI Approved :: MIT License
Classifier: Operating System :: OS Independent
Requires-Python: >=3.6
License-File: LICENSE
Requires-Dist: pytest>=8.3.2
Requires-Dist: pytest-cov>=5.0.0
Requires-Dist: twine>=5.1.1
Requires-Dist: httpx>=0.27.0
Requires-Dist: dacite>=1.8.1
Requires-Dist: pytest-mock>=3.14.0
Requires-Dist: pytest-asyncio>=0.23.8
Requires-Dist: ruff>=0.6.1
Dynamic: author
Dynamic: classifier
Dynamic: description
Dynamic: description-content-type
Dynamic: home-page
Dynamic: keywords
Dynamic: license-file
Dynamic: requires-dist
Dynamic: requires-python
